stretchme/__init__.py
stretchme/default_parameters.py
stretchme/simulations.py
stretchme/stretching_tools.py
stretchme/structure.py
stretchme/trace.py
Stretchme-0.2.dist-info/LICENSE
Stretchme-0.2.dist-info/METADATA
Stretchme-0.2.dist-info/WHEEL
Stretchme-0.2.dist-info/top_level.txt
Stretchme-0.2.dist-info/RECORD
